jexon/REQUIREMENTS
jexon/VERSION
jexon/__init__.py
jexon/execute.py
jexon/internal.py
jexon-0.0.1.dist-info/LICENSE
jexon-0.0.1.dist-info/METADATA
jexon-0.0.1.dist-info/WHEEL
jexon-0.0.1.dist-info/top_level.txt
jexon-0.0.1.dist-info/RECORD
